django_wordle_auth/__init__.py
django_wordle_auth/apps.py
django_wordle_auth/backends.py
django_wordle_auth/checks.py
django_wordle_auth/words.py
tests/__init__.py
tests/test_auth.py
tests/test_checks.py
django_wordle_auth-2022.4.1.dist-info/LICENSE
django_wordle_auth-2022.4.1.dist-info/METADATA
django_wordle_auth-2022.4.1.dist-info/WHEEL
django_wordle_auth-2022.4.1.dist-info/top_level.txt
django_wordle_auth-2022.4.1.dist-info/RECORD
